{
  "incident_id": "INC-1040",
  "title": "payment-service DB deadlocks spiking \u2014 23% payment failure rate",
  "service": "payment-service",
  "severity": "SEV1",
  "timestamp": "2025-01-23T15:00:00Z",
  "resolved_at": "2024-10-23T12:08:00Z",
  "duration_minutes": 49,
  "symptoms": [
    "MySQL: 'Deadlock found when trying to get lock; try restarting transaction'",
    "POST /payments error rate: 0.1% \u2192 23% within 6 minutes of deploy",
    "p99 payment latency: 45 ms \u2192 14 000 ms",
    "Retry storms from iOS/Android clients amplifying deadlock contention",
    "Slow query log: SELECT FOR UPDATE on idempotency_keys holding locks >8 s"
  ],
  "root_cause": "The idempotency lock (SELECT FOR UPDATE on idempotency_keys) is held while waiting for Stripe's response, which takes 2\u20138 s. A mobile client that retries after a network timeout creates a second request with the same idempotency key. Both requests acquire overlapping row locks \u2014 one on idempotency_keys, one on payment_transactions \u2014 in opposite order, creating a classic AB/BA deadlock. Mobile retry logic amplifies this: each deadlock triggers 3 retries, worsening contention exponentially under load.",
  "resolution": "Replaced SELECT FOR UPDATE with INSERT ... ON DUPLICATE KEY UPDATE (optimistic lock). Moved Stripe API call outside the transaction boundary. Added innodb_lock_wait_timeout=2. Added client-side retry jitter (100\u2013500 ms random backoff) in mobile SDK. Payment failure rate returned to 0.08% within 5 minutes of hotfix.",
  "services_affected": [
    "payment-service",
    "checkout-service"
  ],
  "related_prs": [
    "PR-109"
  ],
  "oncall_engineer": "alice_chen",
  "postmortem_url": "https://wiki.internal/postmortems/inc-1009",
  "scenario_id": null
}